vastaanottaa/__init__.py
vastaanottaa/__main__.py
vastaanottaa/cli.py
vastaanottaa-2023.6.17.dist-info/LICENSE
vastaanottaa-2023.6.17.dist-info/METADATA
vastaanottaa-2023.6.17.dist-info/WHEEL
vastaanottaa-2023.6.17.dist-info/entry_points.txt
vastaanottaa-2023.6.17.dist-info/top_level.txt
vastaanottaa-2023.6.17.dist-info/RECORD
