Metadata-Version: 2.1
Name: vastaanottaa
Version: 2023.6.17
Summary: Receive (Finnish: vastaanottaa) text traversing unknown territories.
Author-email: Stefan Hagen <stefan@hagen.link>
Maintainer-email: Stefan Hagen <stefan@hagen.link>
Project-URL: Homepage, https://git.sr.ht/~sthagen/vastaanottaa
Project-URL: Bug-Tracker, https://todo.sr.ht/~sthagen/vastaanottaa
Project-URL: Documentation, https://codes.dilettant.life/docs/vastaanottaa
Project-URL: Source-Code, https://git.sr.ht/~sthagen/vastaanottaa
Project-URL: Test-Coverage, https://codes.dilettant.life/coverage/vastaanottaa
Keywords: developer-tools,devops
Classifier: Development Status :: 3 - Alpha
Classifier: Intended Audience :: Developers
Classifier: License :: OSI Approved :: MIT License
Classifier: Programming Language :: Python :: 3.10
Classifier: Programming Language :: Python :: 3.10
Classifier: Programming Language :: Python :: 3.12
Classifier: Programming Language :: Python :: 3.9
Requires-Python: >=3.9
License-File: LICENSE
Requires-Dist: cryptography (>=41.0.1)
Provides-Extra: dev
Requires-Dist: black ; extra == 'dev'
Requires-Dist: coverage ; extra == 'dev'
Requires-Dist: hypothesis ; extra == 'dev'
Requires-Dist: mypy ; extra == 'dev'
Requires-Dist: pytest ; extra == 'dev'
Requires-Dist: pytest-cov ; extra == 'dev'
Requires-Dist: pytest-flake8 ; extra == 'dev'
Requires-Dist: ruff ; extra == 'dev'
